imbalanced_metrics/__init__.py
imbalanced_metrics/classification_metrics.py
imbalanced_metrics/regression_metrics.py
imbalanced_metrics-0.0.3.dist-info/LICENSE
imbalanced_metrics-0.0.3.dist-info/METADATA
imbalanced_metrics-0.0.3.dist-info/WHEEL
imbalanced_metrics-0.0.3.dist-info/top_level.txt
imbalanced_metrics-0.0.3.dist-info/RECORD
