Metadata-Version: 2.1
Name: imbalanced-metrics
Version: 0.0.3
Summary: Perfromance metrics for imbalanced classification and imbalanced regression tasks
Home-page: https://github.com/paobranco/ImbalanceMetrics
Author: Sadid Rafsun Tulon, Jean-Gabriel Gaudreault, Paula Branco
Author-email: stulo080@uottawa.ca, j.gaudreault@uottawa.ca, pbranco@uottawa.ca
Keywords: imbalanced learning,classification,regression,metrics
Classifier: Programming Language :: Python :: 3
Classifier: Intended Audience :: Developers
Classifier: Intended Audience :: Science/Research
Classifier: Intended Audience :: Education
Classifier: Topic :: Scientific/Engineering
Classifier: Topic :: Scientific/Engineering :: Mathematics
Classifier: Topic :: Scientific/Engineering :: Artificial Intelligence
Classifier: License :: OSI Approved :: GNU General Public License v3 (GPLv3)
License-File: LICENSE
Requires-Dist: scikit-learn
Requires-Dist: numpy
Requires-Dist: smogn
Requires-Dist: pandas
